beans_logging/__init__.py
beans_logging/__version__.py
beans_logging/_builder.py
beans_logging/_constants.py
beans_logging/_core.py
beans_logging/_intercept.py
beans_logging/auto.py
beans_logging/config.py
beans_logging/filters.py
beans_logging/formats.py
beans_logging/rotators.py
beans_logging/schemas.py
beans_logging/sinks.py
beans_logging-7.1.0.dist-info/licenses/LICENSE.txt
beans_logging-7.1.0.dist-info/METADATA
beans_logging-7.1.0.dist-info/WHEEL
beans_logging-7.1.0.dist-info/top_level.txt
beans_logging-7.1.0.dist-info/RECORD
